netam/__init__.py
netam/attention_map.py
netam/cli.py
netam/common.py
netam/dasm.py
netam/dnsm.py
netam/dxsm.py
netam/framework.py
netam/hit_class.py
netam/hyper_burrito.py
netam/models.py
netam/molevol.py
netam/multihit.py
netam/pretrained.py
netam/sequences.py
netam-0.2.1.dist-info/METADATA
netam-0.2.1.dist-info/WHEEL
netam-0.2.1.dist-info/entry_points.txt
netam-0.2.1.dist-info/top_level.txt
netam-0.2.1.dist-info/RECORD
