Metadata-Version: 2.1
Name: netam
Version: 0.2.1
Summary: Neural network models for antibody affinity maturation
Home-page: https://github.com/matsengrp/netam.git
Author: Matsen Group
Author-email: ematsen@gmail.com
Classifier: Development Status :: 3 - Alpha
Classifier: Intended Audience :: Science/Research
Classifier: License :: OSI Approved :: MIT License
Classifier: Natural Language :: English
Classifier: Programming Language :: Python :: 3.9
Requires-Python: >=3.9,<3.12
Requires-Dist: biopython
Requires-Dist: natsort
Requires-Dist: optuna
Requires-Dist: pandas
Requires-Dist: pyyaml
Requires-Dist: requests
Requires-Dist: tensorboardX
Requires-Dist: torch
Requires-Dist: tqdm
Requires-Dist: fire
